genai_telemetry/__init__.py
genai_telemetry/py.typed
genai_telemetry_splunk-2.1.3.dist-info/licenses/LICENSE
genai_telemetry_splunk-2.1.3.dist-info/METADATA
genai_telemetry_splunk-2.1.3.dist-info/WHEEL
genai_telemetry_splunk-2.1.3.dist-info/top_level.txt
genai_telemetry_splunk-2.1.3.dist-info/RECORD
