Metadata-Version: 2.4
Name: genai-telemetry-splunk
Version: 2.1.3
Summary: GenAI/LLM Observability SDK for Splunk - trace LLM calls, RAG pipelines, and AI agents
Author-email: Kamal Bisht <kamalbisht345@gmail.com>
Maintainer-email: Kamal Bisht <kamalbisht345@gmail.com>
License: MIT
Project-URL: Homepage, https://github.com/kamalbisht/genai-telemetry-splunk
Project-URL: Documentation, https://github.com/kamalbisht/genai-telemetry-splunk#readme
Project-URL: Repository, https://github.com/kamalbisht/genai-telemetry-splunk
Project-URL: Issues, https://github.com/kamalbisht/genai-telemetry-splunk/issues
Keywords: genai,llm,observability,splunk,telemetry,tracing,openai,anthropic,langchain,rag,ai,monitoring
Classifier: Development Status :: 4 - Beta
Classifier: Intended Audience :: Developers
Classifier: License :: OSI Approved :: MIT License
Classifier: Operating System :: OS Independent
Classifier: Programming Language :: Python :: 3
Classifier: Programming Language :: Python :: 3.8
Classifier: Programming Language :: Python :: 3.9
Classifier: Programming Language :: Python :: 3.10
Classifier: Programming Language :: Python :: 3.11
Classifier: Programming Language :: Python :: 3.12
Classifier: Topic :: Software Development :: Libraries :: Python Modules
Classifier: Topic :: System :: Monitoring
Classifier: Topic :: Scientific/Engineering :: Artificial Intelligence
Requires-Python: >=3.8
License-File: LICENSE
Provides-Extra: dev
Requires-Dist: pytest>=7.0; extra == "dev"
Requires-Dist: pytest-cov>=4.0; extra == "dev"
Requires-Dist: black>=23.0; extra == "dev"
Requires-Dist: isort>=5.0; extra == "dev"
Requires-Dist: mypy>=1.0; extra == "dev"
Provides-Extra: openai
Requires-Dist: openai>=1.0; extra == "openai"
Provides-Extra: anthropic
Requires-Dist: anthropic>=0.18; extra == "anthropic"
Provides-Extra: langchain
Requires-Dist: langchain>=0.1; extra == "langchain"
Provides-Extra: all
Requires-Dist: openai>=1.0; extra == "all"
Requires-Dist: anthropic>=0.18; extra == "all"
Requires-Dist: langchain>=0.1; extra == "all"
Dynamic: license-file
